markdown_analyzer_lib/__init__.py
markdown_analyzer_lib/markdown_analyzer.py
markdown_analyzer_lib-0.2.0.dist-info/licenses/LICENSE
markdown_analyzer_lib-0.2.0.dist-info/METADATA
markdown_analyzer_lib-0.2.0.dist-info/WHEEL
markdown_analyzer_lib-0.2.0.dist-info/top_level.txt
markdown_analyzer_lib-0.2.0.dist-info/RECORD
