Metadata-Version: 2.4
Name: markdown-analyzer-lib
Version: 0.2.0
Summary: A Python library for parsing, analyzing, and converting Markdown and MDX documents, and converting websites to Markdown.
Author-email: RAFIK <rafiqulislam.mca18.du@gmail.com>, Parmeesh Singh <parmeesh.singh.2580@gmail.com>, Tushar Sirohi <tushar.sirohi21@gmail.com>
License: MIT
Project-URL: Homepage, https://github.com/rafiqul0396/markdown_extractor
Project-URL: Bug Tracker, https://github.com/rafiqul0396/markdown_extractor/issues
Classifier: Development Status :: 3 - Alpha
Classifier: Intended Audience :: Developers
Classifier: Programming Language :: Python :: 3
Classifier: Programming Language :: Python :: 3.7
Classifier: Programming Language :: Python :: 3.8
Classifier: Programming Language :: Python :: 3.9
Classifier: Programming Language :: Python :: 3.10
Classifier: Programming Language :: Python :: 3.11
Classifier: Programming Language :: Python :: 3.12
Classifier: Topic :: Software Development :: Libraries :: Python Modules
Classifier: Topic :: Text Processing :: Markup :: Markdown
Requires-Python: >=3.7
License-File: LICENSE
Requires-Dist: requests
Requires-Dist: beautifulsoup4
Requires-Dist: markdownify
Dynamic: license-file
